qiskit_ibm_provider/VERSION.txt
qiskit_ibm_provider/__init__.py
qiskit_ibm_provider/apiconstants.py
qiskit_ibm_provider/exceptions.py
qiskit_ibm_provider/hub_group_project.py
qiskit_ibm_provider/ibm_backend.py
qiskit_ibm_provider/ibm_backend_service.py
qiskit_ibm_provider/ibm_provider.py
qiskit_ibm_provider/ibm_qubit_properties.py
qiskit_ibm_provider/session.py
qiskit_ibm_provider/version.py
qiskit_ibm_provider/accounts/__init__.py
qiskit_ibm_provider/accounts/account.py
qiskit_ibm_provider/accounts/exceptions.py
qiskit_ibm_provider/accounts/management.py
qiskit_ibm_provider/accounts/storage.py
qiskit_ibm_provider/api/__init__.py
qiskit_ibm_provider/api/auth.py
qiskit_ibm_provider/api/client_parameters.py
qiskit_ibm_provider/api/exceptions.py
qiskit_ibm_provider/api/session.py
qiskit_ibm_provider/api/clients/__init__.py
qiskit_ibm_provider/api/clients/account.py
qiskit_ibm_provider/api/clients/auth.py
qiskit_ibm_provider/api/clients/base.py
qiskit_ibm_provider/api/clients/runtime.py
qiskit_ibm_provider/api/clients/runtime_ws.py
qiskit_ibm_provider/api/clients/version.py
qiskit_ibm_provider/api/clients/websocket.py
qiskit_ibm_provider/api/rest/__init__.py
qiskit_ibm_provider/api/rest/backend.py
qiskit_ibm_provider/api/rest/base.py
qiskit_ibm_provider/api/rest/job.py
qiskit_ibm_provider/api/rest/program_job.py
qiskit_ibm_provider/api/rest/root.py
qiskit_ibm_provider/api/rest/runtime.py
qiskit_ibm_provider/api/rest/runtime_session.py
qiskit_ibm_provider/api/rest/utils/__init__.py
qiskit_ibm_provider/api/rest/utils/data_mapper.py
qiskit_ibm_provider/job/__init__.py
qiskit_ibm_provider/job/constants.py
qiskit_ibm_provider/job/exceptions.py
qiskit_ibm_provider/job/ibm_circuit_job.py
qiskit_ibm_provider/job/ibm_composite_job.py
qiskit_ibm_provider/job/ibm_job.py
qiskit_ibm_provider/job/job_monitor.py
qiskit_ibm_provider/job/queueinfo.py
qiskit_ibm_provider/job/sub_job.py
qiskit_ibm_provider/job/utils.py
qiskit_ibm_provider/jupyter/__init__.py
qiskit_ibm_provider-0.10.0.dist-info/LICENSE.txt
qiskit_ibm_provider-0.10.0.dist-info/METADATA
qiskit_ibm_provider-0.10.0.dist-info/WHEEL
qiskit_ibm_provider-0.10.0.dist-info/entry_points.txt
qiskit_ibm_provider-0.10.0.dist-info/top_level.txt
qiskit_ibm_provider-0.10.0.dist-info/RECORD
