Metadata-Version: 2.1
Name: qiskit-ibm-provider
Version: 0.10.0
Summary: Qiskit IBM Quantum Provider for accessing the quantum devices and simulators at IBM
Home-page: https://github.com/Qiskit/qiskit-ibm-provider
Author: Qiskit Development Team
Author-email: qiskit@us.ibm.com
License: Apache 2.0
Project-URL: Bug Tracker, https://github.com/Qiskit/qiskit-ibm-provider/issues
Project-URL: Documentation, https://docs.quantum.ibm.com/api/qiskit-ibm-provider/
Project-URL: Source Code, https://github.com/Qiskit/qiskit-ibm-provider
Keywords: qiskit,quantum
Classifier: Environment :: Console
Classifier: License :: OSI Approved :: Apache Software License
Classifier: Intended Audience :: Developers
Classifier: Intended Audience :: Science/Research
Classifier: Operating System :: Microsoft :: Windows
Classifier: Operating System :: MacOS
Classifier: Operating System :: POSIX :: Linux
Classifier: Programming Language :: Python :: 3 :: Only
Classifier: Programming Language :: Python :: 3.8
Classifier: Programming Language :: Python :: 3.9
Classifier: Programming Language :: Python :: 3.10
Classifier: Programming Language :: Python :: 3.11
Classifier: Topic :: Scientific/Engineering
Requires-Python: >=3.8
License-File: LICENSE.txt
Requires-Dist: qiskit>=0.45.0
Requires-Dist: requests>=2.19
Requires-Dist: requests-ntlm>=1.1.0
Requires-Dist: numpy>=1.13
Requires-Dist: urllib3>=1.21.1
Requires-Dist: python-dateutil>=2.8.0
Requires-Dist: websocket-client>=1.5.1
Requires-Dist: websockets>=10.0
Requires-Dist: typing_extensions>=4.3
Provides-Extra: visualization
Requires-Dist: matplotlib>=2.1; extra == "visualization"
Requires-Dist: ipywidgets<8.0.0; extra == "visualization"
Requires-Dist: seaborn>=0.9.0; extra == "visualization"
Requires-Dist: plotly>=4.4; extra == "visualization"
Requires-Dist: ipyvuetify>=1.1; extra == "visualization"
Requires-Dist: pyperclip>=1.7; extra == "visualization"
Requires-Dist: ipython>=5.0.0; extra == "visualization"
Requires-Dist: traitlets!=5.0.5; extra == "visualization"
Requires-Dist: ipyvue>=1.8.5; extra == "visualization"
